marv_api/__init__.py
marv_api/dag.py
marv_api/decorators.py
marv_api/deprecation.py
marv_api/ioctrl.py
marv_api/iomsgs.py
marv_api/scanner.py
marv_api/setid.py
marv_api/utils.py
marv_api/tests/__init__.py
marv_api/tests/test_dag.py
marv_api/tests/test_decorators.py
marv_api/tests/test_setid.py
marv_api/tests/test_utils.py
marv_api/tests/types.capnp
marv_api/types/__init__.py
marv_detail/__init__.py
marv_detail/types.capnp
marv_nodes/__init__.py
marv_nodes/types.capnp
marv_pycapnp/__init__.py
marv_pycapnp/types.capnp
marv_pycapnp/tests/__init__.py
marv_pycapnp/tests/conftest.py
marv_pycapnp/tests/pythonic.capnp
marv_pycapnp/tests/test.py
marv_pycapnp/tests/test_wrapper.capnp
marv_pycapnp/tests/test_wrapper.py
marv_api-21.12.0.dist-info/LICENSE.txt
marv_api-21.12.0.dist-info/METADATA
marv_api-21.12.0.dist-info/WHEEL
marv_api-21.12.0.dist-info/top_level.txt
marv_api-21.12.0.dist-info/RECORD
